requests_panel/__init__.py
requests_panel/panel.py
requests_panel/static/requests_panel/js/panel.js
requests_panel/templates/requests_panel/panel.html
django_http_requests_debug_toolbar-0.0.8.dist-info/LICENSE
django_http_requests_debug_toolbar-0.0.8.dist-info/METADATA
django_http_requests_debug_toolbar-0.0.8.dist-info/WHEEL
django_http_requests_debug_toolbar-0.0.8.dist-info/top_level.txt
django_http_requests_debug_toolbar-0.0.8.dist-info/RECORD
