Metadata-Version: 2.1
Name: django-http-requests-debug-toolbar
Version: 0.0.8
Summary: A Django Debug Toolbar panel for Requests
Home-page: 
Author: Alexey Mokeev, Marcel Tschopp
Author-email: mokeev@group-ib.com
License: MIT
Keywords: django django-debug-toolbar requests debug toolbar
Platform: UNKNOWN
Classifier: Environment :: Web Environment
Classifier: Framework :: Django
Classifier: Framework :: Django :: 2.2
Classifier: Intended Audience :: Developers
Classifier: Operating System :: OS Independent
Classifier: License :: OSI Approved :: MIT License
Classifier: Programming Language :: Python
Classifier: Programming Language :: Python :: 3.6
Classifier: Programming Language :: Python :: 3.7
Classifier: Programming Language :: Python :: 3.8
License-File: LICENSE
Requires-Dist: django-debug-toolbar (>=2.2)
